{
  "modelVersion" : "2.2",
  "id" : "elaborarPropostaTecnica",
  "name" : "elaborarPropostaTecnica",
  "lastUpdate" : 1655200272500,
  "rows" : [
    [
      {
        "type" : "container",
        "dimension" : {
          "xs" : 12
        },
        "propertyValues" : { },
        "reference" : "a66bbffd-5de7-4e2e-92f1-a2339145d72d",
        "hasValidationError" : false,
        "id" : "pbContainer",
        "rows" : [
          [
            {
              "type" : "component",
              "dimension" : {
                "md" : 12,
                "sm" : 12,
                "xs" : 12,
                "lg" : 12
              },
              "propertyValues" : {
                "hidden" : {
                  "type" : "constant",
                  "value" : false
                },
                "level" : {
                  "type" : "constant",
                  "value" : "Level 1"
                },
                "cssClasses" : {
                  "type" : "constant",
                  "value" : ""
                },
                "text" : {
                  "type" : "interpolation",
                  "value" : "{{ task.displayName }}"
                },
                "alignment" : {
                  "type" : "constant",
                  "value" : "center"
                },
                "dimension" : {
                  "type" : "constant",
                  "value" : 12
                }
              },
              "reference" : "c73664f3-7eb8-4f75-856a-44b7c9f601e9",
              "hasValidationError" : false,
              "id" : "pbTitle",
              "description" : ""
            }
          ],
          [
            {
              "type" : "component",
              "dimension" : {
                "md" : 12,
                "sm" : 12,
                "xs" : 12,
                "lg" : 12
              },
              "propertyValues" : {
                "allowHtml" : {
                  "type" : "constant",
                  "value" : true
                },
                "labelHidden" : {
                  "type" : "constant",
                  "value" : true
                },
                "hidden" : {
                  "type" : "constant",
                  "value" : false
                },
                "cssClasses" : {
                  "type" : "constant",
                  "value" : ""
                },
                "label" : {
                  "type" : "interpolation"
                },
                "text" : {
                  "type" : "interpolation",
                  "value" : "{{ task.displayDescription }}"
                },
                "alignment" : {
                  "type" : "constant",
                  "value" : "left"
                },
                "dimension" : {
                  "type" : "constant",
                  "value" : 12
                }
              },
              "reference" : "27427cb4-f71c-4b4c-b2cf-0682cafc87f7",
              "hasValidationError" : false,
              "id" : "pbText",
              "description" : ""
            }
          ]
        ]
      }
    ],
    [
      {
        "type" : "formContainer",
        "dimension" : {
          "xs" : 12
        },
        "propertyValues" : { },
        "reference" : "94aabdde-adf1-40ce-86b4-3cd1f4ef9bec",
        "hasValidationError" : false,
        "id" : "pbFormContainer",
        "container" : {
          "type" : "container",
          "dimension" : {
            "xs" : 12
          },
          "propertyValues" : { },
          "reference" : "ce5efe8c-a59e-4a7b-b9a1-a79134e1d8a7",
          "hasValidationError" : false,
          "id" : "pbContainer",
          "rows" : [
            [
              {
                "type" : "component",
                "dimension" : {
                  "md" : 12,
                  "sm" : 12,
                  "xs" : 12,
                  "lg" : 12
                },
                "propertyValues" : {
                  "hidden" : {
                    "type" : "constant",
                    "value" : false
                  },
                  "level" : {
                    "type" : "constant",
                    "value" : "Level 4"
                  },
                  "cssClasses" : {
                    "type" : "constant",
                    "value" : ""
                  },
                  "text" : {
                    "type" : "interpolation",
                    "value" : "Proposta"
                  },
                  "alignment" : {
                    "type" : "constant",
                    "value" : "left"
                  },
                  "dimension" : {
                    "type" : "constant",
                    "value" : 12
                  }
                },
                "reference" : "dd11771e-1722-4b29-90b1-f2f1e0b0cfa8",
                "hasValidationError" : false,
                "id" : "pbTitle",
                "description" : ""
              }
            ],
            [
              {
                "type" : "container",
                "dimension" : {
                  "md" : 12,
                  "sm" : 12,
                  "xs" : 12,
                  "lg" : 12
                },
                "propertyValues" : {
                  "repeatedCollection" : {
                    "type" : "variable"
                  },
                  "hidden" : {
                    "type" : "constant",
                    "value" : false
                  },
                  "cssClasses" : {
                    "type" : "constant",
                    "value" : ""
                  },
                  "dimension" : {
                    "type" : "constant",
                    "value" : 12
                  }
                },
                "reference" : "0a931447-a36a-4b75-bf4b-b15759c22194",
                "hasValidationError" : false,
                "id" : "pbContainer",
                "rows" : [
                  [
                    {
                      "type" : "component",
                      "dimension" : {
                        "md" : 12,
                        "sm" : 12,
                        "xs" : 12,
                        "lg" : 12
                      },
                      "propertyValues" : {
                        "allowHtml" : {
                          "type" : "constant",
                          "value" : true
                        },
                        "labelHidden" : {
                          "type" : "constant",
                          "value" : false
                        },
                        "hidden" : {
                          "type" : "expression",
                          "value" : "!proposta.necessidadesCliente"
                        },
                        "cssClasses" : {
                          "type" : "constant",
                          "value" : ""
                        },
                        "label" : {
                          "type" : "interpolation",
                          "value" : "Necessidades Cliente"
                        },
                        "text" : {
                          "type" : "interpolation",
                          "value" : "{{proposta.necessidadesCliente}}"
                        },
                        "alignment" : {
                          "type" : "constant",
                          "value" : "left"
                        },
                        "dimension" : {
                          "type" : "constant",
                          "value" : 12
                        },
                        "labelPosition" : {
                          "type" : "constant",
                          "value" : "top"
                        },
                        "labelWidth" : {
                          "type" : "constant",
                          "value" : 4
                        },
                        "allowHTML" : {
                          "type" : "constant",
                          "value" : true
                        }
                      },
                      "reference" : "b2fd6b54-0d6a-4d8b-bc0b-4df72e5c254a",
                      "hasValidationError" : false,
                      "id" : "pbText",
                      "description" : ""
                    }
                  ],
                  [
                    {
                      "type" : "component",
                      "dimension" : {
                        "md" : 12,
                        "sm" : 12,
                        "xs" : 12,
                        "lg" : 12
                      },
                      "propertyValues" : {
                        "labelHidden" : {
                          "type" : "constant",
                          "value" : false
                        },
                        "hidden" : {
                          "type" : "expression",
                          "value" : "!proposta.standard"
                        },
                        "cssClasses" : {
                          "type" : "constant",
                          "value" : ""
                        },
                        "disabled" : {
                          "type" : "constant",
                          "value" : true
                        },
                        "label" : {
                          "type" : "interpolation",
                          "value" : "Standard"
                        },
                        "dimension" : {
                          "type" : "constant",
                          "value" : 12
                        },
                        "value" : {
                          "type" : "variable",
                          "value" : "proposta.standard"
                        },
                        "required" : {
                          "type" : "constant",
                          "value" : false
                        }
                      },
                      "reference" : "d5b02dcf-7809-4fa3-9c53-cf2be98bf3f8",
                      "hasValidationError" : false,
                      "id" : "pbCheckbox",
                      "description" : ""
                    }
                  ],
                  [
                    {
                      "type" : "component",
                      "dimension" : {
                        "md" : 12,
                        "sm" : 12,
                        "xs" : 12,
                        "lg" : 12
                      },
                      "propertyValues" : {
                        "allowHtml" : {
                          "type" : "constant",
                          "value" : true
                        },
                        "labelHidden" : {
                          "type" : "constant",
                          "value" : false
                        },
                        "hidden" : {
                          "type" : "expression",
                          "value" : "!proposta.requesitos"
                        },
                        "cssClasses" : {
                          "type" : "constant",
                          "value" : ""
                        },
                        "label" : {
                          "type" : "interpolation",
                          "value" : "Requesitos"
                        },
                        "text" : {
                          "type" : "interpolation",
                          "value" : "{{proposta.requesitos}}"
                        },
                        "alignment" : {
                          "type" : "constant",
                          "value" : "left"
                        },
                        "dimension" : {
                          "type" : "constant",
                          "value" : 12
                        },
                        "labelPosition" : {
                          "type" : "constant",
                          "value" : "top"
                        },
                        "labelWidth" : {
                          "type" : "constant",
                          "value" : 4
                        },
                        "allowHTML" : {
                          "type" : "constant",
                          "value" : true
                        }
                      },
                      "reference" : "f0350ca7-3fa0-4fd3-b202-20181e9c33bd",
                      "hasValidationError" : false,
                      "id" : "pbText",
                      "description" : ""
                    }
                  ],
                  [
                    {
                      "type" : "component",
                      "dimension" : {
                        "md" : 12,
                        "sm" : 12,
                        "xs" : 12,
                        "lg" : 12
                      },
                      "propertyValues" : {
                        "labelHidden" : {
                          "type" : "constant",
                          "value" : false
                        },
                        "hidden" : {
                          "type" : "constant",
                          "value" : false
                        },
                        "labelPosition" : {
                          "type" : "constant",
                          "value" : "top"
                        },
                        "cssClasses" : {
                          "type" : "constant",
                          "value" : ""
                        },
                        "labelWidth" : {
                          "type" : "constant",
                          "value" : 1
                        },
                        "readOnly" : {
                          "type" : "constant",
                          "value" : false
                        },
                        "label" : {
                          "type" : "interpolation",
                          "value" : "Proposta Tecnica"
                        },
                        "placeholder" : {
                          "type" : "constant"
                        },
                        "type" : {
                          "type" : "constant",
                          "value" : "text"
                        },
                        "dimension" : {
                          "type" : "constant",
                          "value" : 12
                        },
                        "value" : {
                          "type" : "variable",
                          "value" : "proposta.propostaTecnica"
                        },
                        "required" : {
                          "type" : "constant",
                          "value" : false
                        },
                        "minLength" : {
                          "type" : "constant",
                          "value" : ""
                        },
                        "maxLength" : {
                          "type" : "constant",
                          "value" : ""
                        },
                        "min" : {
                          "type" : "constant"
                        },
                        "max" : {
                          "type" : "constant"
                        },
                        "step" : {
                          "type" : "constant",
                          "value" : 1
                        }
                      },
                      "reference" : "26f188ec-f779-48e7-bd5e-40c2226dd048",
                      "hasValidationError" : false,
                      "id" : "pbInput",
                      "description" : ""
                    }
                  ]
                ]
              }
            ],
            [
              {
                "type" : "component",
                "dimension" : {
                  "md" : 12,
                  "sm" : 12,
                  "xs" : 12,
                  "lg" : 12
                },
                "propertyValues" : {
                  "removeItem" : {
                    "type" : "variable"
                  },
                  "hidden" : {
                    "type" : "constant",
                    "value" : false
                  },
                  "cssClasses" : {
                    "type" : "constant",
                    "value" : ""
                  },
                  "buttonStyle" : {
                    "type" : "constant",
                    "value" : "primary"
                  },
                  "label" : {
                    "type" : "interpolation",
                    "value" : "Submit"
                  },
                  "dataToSend" : {
                    "type" : "expression",
                    "value" : "formOutput"
                  },
                  "dataFromError" : {
                    "type" : "variable",
                    "value" : "formOutput._submitError"
                  },
                  "labelHidden" : {
                    "type" : "constant",
                    "value" : false
                  },
                  "collectionPosition" : {
                    "type" : "constant"
                  },
                  "targetUrlOnSuccess" : {
                    "type" : "interpolation",
                    "value" : "/bonita"
                  },
                  "action" : {
                    "type" : "constant",
                    "value" : "Submit task"
                  },
                  "collectionToModify" : {
                    "type" : "variable"
                  },
                  "valueToAdd" : {
                    "type" : "expression"
                  },
                  "disabled" : {
                    "type" : "expression",
                    "value" : "$form.$invalid"
                  },
                  "alignment" : {
                    "type" : "constant",
                    "value" : "center"
                  },
                  "dimension" : {
                    "type" : "constant",
                    "value" : 12
                  }
                },
                "reference" : "56921ca6-bcbc-47c1-bf8a-076f40979c0e",
                "hasValidationError" : false,
                "id" : "pbButton",
                "description" : ""
              }
            ],
            [
              {
                "type" : "component",
                "dimension" : {
                  "md" : 12,
                  "sm" : 12,
                  "xs" : 12,
                  "lg" : 12
                },
                "propertyValues" : {
                  "allowHTML" : {
                    "type" : "constant",
                    "value" : true
                  },
                  "allowHtml" : {
                    "type" : "constant",
                    "value" : true
                  },
                  "labelHidden" : {
                    "type" : "constant",
                    "value" : true
                  },
                  "hidden" : {
                    "type" : "expression",
                    "value" : "!formOutput._submitError.message"
                  },
                  "cssClasses" : {
                    "type" : "constant",
                    "value" : "alert alert-danger col-lg-6 col-lg-offset-3"
                  },
                  "label" : {
                    "type" : "interpolation"
                  },
                  "text" : {
                    "type" : "interpolation",
                    "value" : "<strong>Debug message</strong>\n<br/>\n{{formOutput._submitError.message}}\n{{submit_errors_list}}"
                  },
                  "alignment" : {
                    "type" : "constant",
                    "value" : "left"
                  },
                  "dimension" : {
                    "type" : "constant",
                    "value" : 12
                  }
                },
                "reference" : "a102b7b3-333b-459e-b4ed-7070f8c5a73f",
                "hasValidationError" : false,
                "id" : "pbText",
                "description" : ""
              }
            ]
          ]
        }
      }
    ]
  ],
  "assets" : [
    {
      "id" : "065538b4-87bd-403d-aa76-bcd005156fca",
      "name" : "localization.json",
      "type" : "json",
      "order" : 0,
      "external" : false
    },
    {
      "id" : "9acd1c73-6500-44a6-8e64-4a803e64780b",
      "name" : "style.css",
      "type" : "css",
      "order" : 0,
      "external" : false
    }
  ],
  "inactiveAssets" : [ ],
  "variables" : {
    "task" : {
      "type" : "url",
      "value" : [
        "../API/bpm/userTask/{{taskId}}"
      ],
      "exposed" : false
    },
    "submit_errors_list" : {
      "type" : "expression",
      "value" : [
        "if($data.formOutput && $data.formOutput._submitError && $data.formOutput._submitError.explanations){",
        "\tconst liElements = $data.formOutput._submitError.explanations",
        "\t\t.filter(cause => cause !== null)",
        "\t\t.map(cause => \"<li>\" + cause + \"</li>\")",
        "\t\t.join('');",
        "\tif(liElements){",
        "\t\treturn \"<ul>\" + liElements + \"</ul>\";",
        "\t}",
        "}"
      ],
      "exposed" : false
    },
    "proposta" : {
      "type" : "url",
      "value" : [
        "../{{context.proposta_ref.link}}"
      ],
      "exposed" : false
    },
    "formOutput" : {
      "type" : "expression",
      "value" : [
        "if( $data.proposta ){",
        "\treturn {",
        "\t\t//map proposta variable to expected task contract input",
        "\t\tpropostaInput: {",
        "\t\t\tpropostaTecnica: $data.proposta.propostaTecnica !== undefined ? $data.proposta.propostaTecnica : null",
        "\t\t}",
        "\t}",
        "}"
      ],
      "exposed" : false
    },
    "context" : {
      "type" : "url",
      "value" : [
        "../API/bpm/userTask/{{taskId}}/context"
      ],
      "exposed" : false
    },
    "taskId" : {
      "type" : "urlparameter",
      "value" : [
        "id"
      ],
      "exposed" : false
    }
  },
  "hasValidationError" : false,
  "uuid" : "d7e1e4b2-061a-4792-8ac3-7f82615865de",
  "type" : "form",
  "description" : "Page generated with Bonita UI designer"
}